MANIFEST.in
RELEASE-VERSION
get_git_version.py
setup.py
displays.egg-info/PKG-INFO
displays.egg-info/SOURCES.txt
displays.egg-info/dependency_links.txt
displays.egg-info/entry_points.txt
displays.egg-info/top_level.txt
src/__init__.py
src/main.py
src/table.py