Metadata-Version: 1.0
Name: displays
Version: 0.3.2
Summary: Commandline tool to configure Mac OS X displaymodes
Home-page: http://github.com/bwesterb/displays/
Author: Bas Westerbaan
Author-email: bas@westerbaan.name
License: UNKNOWN
Platform: UNKNOWN
